slashlock.py
slashlock-0.1.5.dist-info/DESCRIPTION.rst
slashlock-0.1.5.dist-info/LICENSE.txt
slashlock-0.1.5.dist-info/METADATA
slashlock-0.1.5.dist-info/RECORD
slashlock-0.1.5.dist-info/WHEEL
slashlock-0.1.5.dist-info/metadata.json
slashlock-0.1.5.dist-info/top_level.txt
