Metadata-Version: 2.0
Name: slashlock
Version: 0.1.5
Summary: Slashlock - A Simple File and Folder Encryptor
Home-page: https://github.com/wookalar/slashlock/blob/master/slashlock.py
Author: Wookalar Software
Author-email: doc.tart@wookalar.io
License: AGPLv3
Platform: UNKNOWN
Requires-Dist: argon2-cffi (>=16.2.0)
Requires-Dist: PyNaCl (>=1.0.1)
